setup.py
overwatch_api/__init__.py
overwatch_api/constants.py
overwatch_api/core.py
overwatch_api/example_test.py
overwatch_api/exceptions.py
overwatch_api.egg-info/PKG-INFO
overwatch_api.egg-info/SOURCES.txt
overwatch_api.egg-info/dependency_links.txt
overwatch_api.egg-info/requires.txt
overwatch_api.egg-info/top_level.txt