Metadata-Version: 1.0
Name: overwatch-api
Version: 0.5
Summary: Overwatch API Wrapper using lootbox.eu
Home-page: http://github.com/anthok/overwatch-api
Author: Kyle Anthony <anthok>
Author-email: UNKNOWN
License: MIT
Platform: UNKNOWN
